tcrdb/__init__.py
tcrdb/tcrdb_dddb.py
tcrdb/version.py
tcrdb-0.0.4.dist-info/LICENSE
tcrdb-0.0.4.dist-info/METADATA
tcrdb-0.0.4.dist-info/WHEEL
tcrdb-0.0.4.dist-info/top_level.txt
tcrdb-0.0.4.dist-info/RECORD
